django_unused/__init__.py
django_unused/admin.py
django_unused/apps.py
django_unused/models.py
django_unused/tests.py
django_unused/views.py
django_unused/management/__init__.py
django_unused/management/commands/__init__.py
django_unused/management/commands/_templates.py
django_unused/management/commands/_views.py
django_unused/management/commands/unused.py
django_unused/migrations/__init__.py
django_unused/unused/__init__.py
django_unused/unused/decorators.py
django_unused/unused/find_media.py
django_unused/unused/find_templates.py
django_unused/unused/find_views.py
django_unused-0.1.4.dist-info/DESCRIPTION.rst
django_unused-0.1.4.dist-info/METADATA
django_unused-0.1.4.dist-info/RECORD
django_unused-0.1.4.dist-info/WHEEL
django_unused-0.1.4.dist-info/metadata.json
django_unused-0.1.4.dist-info/top_level.txt
example/app1/__init__.py
example/app1/models.py
example/app1/urls.py
example/app1/views.py
example/server/__init__.py
example/server/models.py
example/server/settings.py
example/server/urls.py
example/server/wsgi.py
example/server/tests/__init__.py
example/server/tests/test_templates.py
example/server/tests/test_views.py
example/server/views/__init__.py
example/server/views/view_not_named_view.py
example/server/views/sub/__init__.py
example/server/views/sub/view_file.py
