Metadata-Version: 2.0
Name: django-unused
Version: 0.1.4
Summary: Finds unused templates in Django
Home-page: https://github.com/edustaff/django-unused
Author: Kevin Clark
Author-email: kclark@edustaff.org
License: MIT
Keywords: django,templates
Platform: OS Independent
Classifier: Environment :: Web Environment
Classifier: Framework :: Django
Classifier: Intended Audience :: Developers
Classifier: License :: OSI Approved :: MIT License
Classifier: Operating System :: OS Independent
Classifier: Programming Language :: Python
Classifier: Topic :: Software Development :: Libraries :: Python Modules
Classifier: Development Status :: 4 - Beta
Classifier: Programming Language :: Python :: 2.7
Classifier: Programming Language :: Python :: 3.4
Classifier: Programming Language :: Python :: 3.5
Classifier: Programming Language :: Python :: 3.6
